openlake/__init__.py
openlake/cache.py
openlake/fetcher.py
openlake/parser.py
openlake/provider/__init__.py
openlake/provider/kaggle.py
openlake/provider/sklearn.py
openlake-0.6.dist-info/METADATA
openlake-0.6.dist-info/WHEEL
openlake-0.6.dist-info/licenses/LICENSE
openlake-0.6.dist-info/licenses/NOTICE
openlake-0.6.dist-info/RECORD
