Metadata-Version: 2.1
Name: openlake
Version: 0.6
Summary: Public dataset feed.
Project-URL: Source, https://github.com/formlio/openlake/
Project-URL: Documentation, https://openlake.readthedocs.io/
Project-URL: Issues, https://github.com/formlio/openlake/issues/
Maintainer-email: ForML Development Team <info@forml.io>
License: Apache License 2.0
License-File: LICENSE
License-File: NOTICE
Classifier: Development Status :: 4 - Beta
Classifier: Environment :: Console
Classifier: Intended Audience :: Developers
Classifier: Intended Audience :: Science/Research
Classifier: License :: OSI Approved :: Apache Software License
Classifier: Programming Language :: Python :: 3
Classifier: Topic :: Scientific/Engineering :: Artificial Intelligence
Classifier: Topic :: System :: Distributed Computing
Requires-Python: >=3
Requires-Dist: forml[sql]
Requires-Dist: openschema
Requires-Dist: pandas[parquet]
Requires-Dist: sqlalchemy
Provides-Extra: all
Requires-Dist: openlake[kaggle,sklearn]; extra == 'all'
Provides-Extra: dev
Requires-Dist: black; extra == 'dev'
Requires-Dist: flake8-bugbear; extra == 'dev'
Requires-Dist: flake8-colors; extra == 'dev'
Requires-Dist: flake8-typing-imports; extra == 'dev'
Requires-Dist: isort; extra == 'dev'
Requires-Dist: pip-tools; extra == 'dev'
Requires-Dist: pre-commit; extra == 'dev'
Requires-Dist: pycln; extra == 'dev'
Requires-Dist: pylint; extra == 'dev'
Requires-Dist: pytest-cov; extra == 'dev'
Requires-Dist: pytest-xdist; extra == 'dev'
Provides-Extra: docs
Requires-Dist: sphinx; extra == 'docs'
Requires-Dist: sphinx-copybutton; extra == 'docs'
Requires-Dist: sphinx-rtd-theme; extra == 'docs'
Requires-Dist: sphinxcontrib-details-directive; extra == 'docs'
Requires-Dist: sphinxcontrib-napoleon; extra == 'docs'
Requires-Dist: sphinxcontrib-spelling; extra == 'docs'
Provides-Extra: kaggle
Requires-Dist: kaggle; extra == 'kaggle'
Provides-Extra: sklearn
Requires-Dist: scikit-learn; extra == 'sklearn'
